{
  "NONE": "无",
  "ZERO": "0",
  "ONE": "1",
  "TWO": "2",
  "THREE": "3",
  "FOUR": "4",
  "FIVE": "5",
  "SIX": "6",
  "SEVEN": "7",
  "EIGHT": "8",
  "NINE": "9",
  "LEFTMOUSE": "左键",
  "MIDDLEMOUSE": "中键",
  "RIGHTMOUSE": "右键",
  "BUTTON4MOUSE": "鼠标4键",
  "BUTTON5MOUSE": "鼠标5键",
  "BUTTON6MOUSE": "鼠标6键",
  "BUTTON7MOUSE": "鼠标7键",
  "MOUSEMOVE": "鼠标移动",
  "ERASER": "橡皮擦",
  "TRACKPADPAN": "轨迹平移",
  "TRACKPADZOOM": "轨迹推拉",
  "MOUSEROTATE": "鼠标旋转",
  "MOUSESMARTZOOM": "智能缩放",
  "WHEELUPMOUSE": "向上滚动鼠标",
  "WHEELDOWNMOUSE": "向下滚动鼠标",
  "WHEELINMOUSE": "鼠标滚轮向内",
  "WHEELOUTMOUSE": "鼠标滚轮向外",
  "LEFT_CTRL": "Ctrl",
  "LEFT_ALT": "Alt",
  "LEFT_SHIFT": "Shift",
  "RIGHT_ALT": "右Alt",
  "RIGHT_CTRL": "右Ctrl",
  "RIGHT_SHIFT": "右Shift",
  "APP": "App",
  "SEMI_COLON": "分号",
  "OSKEY": "Win",
  "COMMA": ",",
  "QUOTE": "“",
  "ACCENT_GRAVE": "`",
  "MINUS": "-",
  "PLUS": "+",
  "SLASH": "/",
  "BACK_SLASH": "\\",
  "EQUAL": "=",
  "LEFT_BRACKET": "[",
  "RIGHT_BRACKET": "]",
  "LEFT_ARROW": "←",
  "DOWN_ARROW": "↓",
  "RIGHT_ARROW": "→",
  "UP_ARROW": "↑",
  "NUMPAD_2": "小键盘2",
  "NUMPAD_4": "小键盘4",
  "NUMPAD_6": "小键盘6",
  "NUMPAD_8": "小键盘8",
  "NUMPAD_1": "小键盘1",
  "NUMPAD_3": "小键盘3",
  "NUMPAD_5": "小键盘5",
  "NUMPAD_7": "小键盘7",
  "NUMPAD_9": "小键盘9",
  "NUMPAD_PERIOD": "小键盘.",
  "NUMPAD_SLASH": "小键盘/",
  "NUMPAD_ASTERIX": "小键盘*",
  "NUMPAD_0": "小键盘0",
  "NUMPAD_MINUS": "小键盘-",
  "NUMPAD_ENTER": "小键盘确认",
  "NUMPAD_PLUS": "小键盘+",
  "PAUSE": "Pause",
  "INSERT": "Insert",
  "HOME": "Home",
  "PAGE_UP": "上一页",
  "PAGE_DOWN": "下一页",
  "END": "End",
  "MEDIA_PLAY": "⏯",
  "MEDIA_STOP": "⏹",
  "MEDIA_FIRST": "⏮",
  "MEDIA_LAST": "⏭",

  "Window": "窗口",
  "Screen": "屏幕",
  "Screen Editing": "屏幕编辑",
  "User Interface": "用户界面",
  "View2D": "2D视图",
  "View2D Buttons List": "2D视图按钮列表",
  "3D View": "3D视图",
  "Object Mode": "物体模式",
  "Mesh": "网格",
  "Curve": "曲线",
  "Armature": "骨架",
  "Metaball": "融球",
  "Lattice": "晶格",
  "Font": "文字",
  "Pose": "姿态",
  "Vertex Paint": "顶点绘制",
  "Weight Paint": "权重绘制",
  "Image Paint": "图像绘制",
  "Sculpt": "雕刻",
  "Particle": "粒子",
  "Grease Pencil": "蜡笔",
  "Grease Pencil Edit Mode": "蜡笔编辑模式",
  "Grease Pencil Paint Mode": "蜡笔绘制模式",
  "Grease Pencil Sculpt Mode": "蜡笔雕刻模式",
  "Grease Pencil Weight Mode": "蜡笔权重模式",
  "Grease Pencil Vertex Mode": "蜡笔顶点模式",
  "Curves": "毛发曲线",
  "Sculpt Curves": "雕刻曲线",
  "Paint Vertex Selection (Weight, Vertex)": "绘制顶点选择(权重, 顶点)",
  "Paint Face Mask (Weight, Vertex, Texture)": "绘制面遮罩(权重, 顶点, 纹理)",
  "Outliner": "大纲视图",
  "Property Editor": "属性编辑器",
  "File Browser": "文件浏览器",
  "Info": "信息",
  "Text": "文本",
  "Text Generic": "文本 (通用)",
  "Region Context Menu": "区域上下文菜单",
  "Console": "控制台",
  "Clip": "剪辑",
  "Clip Editor": "剪辑编辑器",
  "Clip Graph Editor": "剪辑曲线编辑器",
  "Clip Dopesheet Editor": "剪辑摄影表编辑器",
  "Mask Editing": "遮罩编辑",
  "Frames": "帧",
  "Markers": "标记",
  "Animation": "动画",
  "Dopesheet": "摄影表",
  "Graph Editor": "曲线编辑器",
  "NLA Editor": "NLA编辑器",
  "Image": "图像",
  "UV Editor": "UV编辑器",
  "Sequencer": "序列编辑器",
  "SequencerPreview": "序列预览",
  "Video Sequence Editor": "视频序列编辑器",
  "Node Editor": "节点编辑器",
  "Spreadsheet": "电子表格",
  "Spreadsheet Generic": "电子表格通用",
  "Primitive Tool Modal Map": "基本体工具模态映射",
  "Pen Tool Modal Map": "钢笔工具模态映射",
  "Knife Tool Modal Map": "小刀工具模态映射",
  "Custom Normals Modal Map": "自定义法线模态映射",
  "Bevel Modal Map": "倒角模态映射",
  "Paint Stroke Modal": "绘制笔触模态",
  "Sculpt Expand Modal": "雕刻扩展模态",
  "Curve Pen Modal Map": "曲线钢笔模态映射",
  "View3D Placement Modal": "3D视图放置模态",
  "View3D Walk Modal": "3D视图行走模态",
  "View3D Fly Modal": "3D视图飞行模态",
  "View3D Rotate Modal": "3D视图旋转模态",
  "View3D Move Modal": "3D视图移动模态",
  "View3D Zoom Modal": "3D视图缩放模态",
  "View3D Dolly Modal": "3D视图推拉模态"
}
